sendit/__init__.py
sendit/applications/__init__.py
sendit/applications/arp_daemon.py
sendit/applications/arpmap.py
sendit/applications/async_demo.py
sendit/applications/basic_examples.py
sendit/applications/examples.py
sendit/applications/ipv4_handler.py
sendit/applications/ipv6_handler.py
sendit/handlers/__init__.py
sendit/handlers/arp_handler.py
sendit/handlers/bytes_handler.py
sendit/handlers/ethernet_handler.py
sendit/handlers/handler.py
sendit/handlers/ip_fragmentation_handler.py
sendit/handlers/ipv4_handler.py
sendit/handlers/ipv6_handler.py
sendit/handlers/raw_nic.py
sendit/handlers/tcp_handler.py
sendit/handlers/udp_handler.py
sendit/helper_functions/__init__.py
sendit/helper_functions/helper.py
sendit/helper_functions/ip_protocols.csv
sendit/helper_functions/mal.csv
sendit/helper_functions/mam.csv
sendit/helper_functions/mas.csv
sendit/protocols/__init__.py
sendit/protocols/arp.py
sendit/protocols/etherframe.py
sendit/protocols/ipv4.py
sendit/protocols/ipv6.py
sendit/protocols/tcp.py
sendit/protocols/udp.py
sendit-1.0.8.dist-info/LICENSE
sendit-1.0.8.dist-info/METADATA
sendit-1.0.8.dist-info/WHEEL
sendit-1.0.8.dist-info/top_level.txt
sendit-1.0.8.dist-info/RECORD
