Metadata-Version: 2.1
Name: sendit
Version: 1.0.8
Summary: A package that provides easy access to forming, sending, and listening to custom messages from Layer 2 to Layer 4
Home-page: https://github.com/mbaker-97/networkingpy
Author: Matt Baker
Author-email: mbakervtech@gmail.com
License: UNKNOWN
Platform: UNKNOWN
